CHANGES.rst
LICENSE
MANIFEST.in
README.rst
setup.cfg
setup.py
sphinxcontrib/__init__.py
sphinxcontrib/doxylink/__init__.py
sphinxcontrib/doxylink/doxylink.py
sphinxcontrib/doxylink/parsing.py
sphinxcontrib_doxylink_hotfix.egg-info/PKG-INFO
sphinxcontrib_doxylink_hotfix.egg-info/SOURCES.txt
sphinxcontrib_doxylink_hotfix.egg-info/dependency_links.txt
sphinxcontrib_doxylink_hotfix.egg-info/namespace_packages.txt
sphinxcontrib_doxylink_hotfix.egg-info/requires.txt
sphinxcontrib_doxylink_hotfix.egg-info/top_level.txt