Metadata-Version: 1.2
Name: sphinxcontrib-doxylink-hotfix
Version: 1.6.1
Summary: Sphinx extension for linking to Doxygen documentation.
Home-page: http://sphinxcontrib-doxylink.readthedocs.io/en/stable/
Author: Matt Williams
Author-email: matt@milliams.com
License: BSD
Download-URL: http://pypi.python.org/pypi/sphinxcontrib-doxylink
Keywords: sphinx,doxygen,documentation,c++
Platform: UNKNOWN
Classifier: Development Status :: 5 - Production/Stable
Classifier: Environment :: Console
Classifier: Environment :: Web Environment
Classifier: Intended Audience :: Developers
Classifier: License :: OSI Approved :: BSD License
Classifier: Operating System :: OS Independent
Classifier: Programming Language :: Python :: 3
Classifier: Topic :: Documentation
Classifier: Topic :: Utilities
Requires-Python: ~=3.4
